lizzy_client/__init__.py
lizzy_client/__main__.py
lizzy_client/arguments.py
lizzy_client/cli.py
lizzy_client/configuration.py
lizzy_client/lizzy.py
lizzy_client/metrics.py
lizzy_client/token.py
lizzy_client/utils.py
lizzy_client/version.py
lizzy_client-2.8.4.dist-info/LICENSE.txt
lizzy_client-2.8.4.dist-info/METADATA
lizzy_client-2.8.4.dist-info/WHEEL
lizzy_client-2.8.4.dist-info/entry_points.txt
lizzy_client-2.8.4.dist-info/top_level.txt
lizzy_client-2.8.4.dist-info/RECORD
