Metadata-Version: 2.1
Name: lizzy-client
Version: 2.8.4
Summary: Lizzy-client
Home-page: https://github.com/zalando/lizzy-client
Author: Zalando SE
Author-email: UNKNOWN
License: Apache License Version 2.0
Platform: UNKNOWN
Classifier: Programming Language :: Python
Classifier: Programming Language :: Python :: 3.4
Classifier: Development Status :: 4 - Beta
Classifier: Intended Audience :: Developers
Classifier: Operating System :: OS Independent
Requires-Dist: click (<7.0,>=6.3)
Requires-Dist: clickclick (>=0.15)
Requires-Dist: requests (>=2.9.1)
Requires-Dist: pyyaml (>=3.11)
Requires-Dist: python-dateutil (>=2.5.0)
Requires-Dist: stups-tokens (>=1.0.17)
Requires-Dist: environmental (>=1.0)
Requires-Dist: urlpath (>=1.1.2)
Requires-Dist: typing (>=3.5.0.1)
